aiopurpleair/__init__.py
aiopurpleair/api.py
aiopurpleair/backports/__init__.py
aiopurpleair/backports/enum.py
aiopurpleair/const.py
aiopurpleair/endpoints/__init__.py
aiopurpleair/endpoints/sensors.py
aiopurpleair/errors.py
aiopurpleair/helpers/__init__.py
aiopurpleair/helpers/model.py
aiopurpleair/helpers/validator/__init__.py
aiopurpleair/helpers/validator/sensors.py
aiopurpleair/models/__init__.py
aiopurpleair/models/keys.py
aiopurpleair/models/sensors.py
aiopurpleair/py.typed
aiopurpleair/util/__init__.py
aiopurpleair/util/dt.py
aiopurpleair/util/geo.py
aiopurpleair-2025.8.0.dist-info/LICENSE
aiopurpleair-2025.8.0.dist-info/METADATA
aiopurpleair-2025.8.0.dist-info/WHEEL
aiopurpleair-2025.8.0.dist-info/RECORD
