Metadata-Version: 2.3
Name: aiopurpleair
Version: 2025.8.0
Summary: A Python 3, asyncio-based library to interact with the PurpleAir API
License: MIT
Author: Aaron Bach
Author-email: bachya1208@gmail.com
Requires-Python: >=3.10,<4.0
Classifier: License :: OSI Approved :: MIT License
Classifier: Programming Language :: Python
Classifier: Programming Language :: Python :: 3
Classifier: Programming Language :: Python :: 3.10
Classifier: Programming Language :: Python :: 3.11
Classifier: Programming Language :: Python :: 3.12
Classifier: Programming Language :: Python :: 3.13
Classifier: Programming Language :: Python :: Implementation :: CPython
Classifier: Programming Language :: Python :: Implementation :: PyPy
Requires-Dist: aiohttp (>=3.9.0b0)
Requires-Dist: certifi (>=2023.07.22)
Requires-Dist: pydantic (>=2.0.0,<3.0.0)
Requires-Dist: yarl (>=1.9.2)
Project-URL: Bug Tracker, https://github.com/bachya/aiopurpleair/issues
Project-URL: Changelog, https://github.com/bachya/aiopurpleair/releases
Project-URL: Repository, https://github.com/bachya/aiopurpleair
